{
  "name": "Kusto Vietnam",
  "slug": "kusto-vietnam",
  "type": "Private Equity",
  "website": "https://www.kustogroup.com/",
  "description": "The Kusto Group is a Singapore private holding company with diversified investments in construction materials manufacturing, oil and gas production, energy, development, civil construction, venture/IT and agriculture.\n\nKusto Vietnam belongs to a group of foreign investors, currently investing in markets of Kazakhstan, Russia, China, Turkey and Vietnam. \n\nIn 2005 Kusto Group established BTA Venture Capital Management Company in Vietnam - the predecessor of Kusto Vietnam today. Kusto Group takes the first step into the field of real estate in Vietnam. So far, with continuous efforts, Kusto Group has made great progress when continuously expanding its portfolio.\n\nSome outstanding investment activities of Kusto such as http://Truongxua.vn, http://Everyday.vn, and http://Wada.vn.",
  "location": "Singapore",
  "founded": "2005",
  "facebook": "",
  "linkedin": "",
  "crunchbase": "https://www.crunchbase.com/organization/kusto-group",
  "portfolio": "http://kusto.com.vn/en/portfolio/"
}