{"name": "Masan Group", "slug": "masan-group", "type": "Corporate Venture Capital", "website": "https://www.masangroup.com/", "description": "Masan Group is one of Vietnam’s largest private sector companies with a market capitalization of over US$3 billion, focusing on consumption and resources sectors. Masan is committed to executing shareholder value, through building market-leading businesses with a professional management team and global partners.", "location": "Vietnam", "founded": "1996", "facebook": "", "linkedin": "https://www.linkedin.com/company/masan-group/", "crunchbase": "https://www.crunchbase.com/organization/masan-group", "portfolio": "", "logoUrl": "/img/investor/masan-group-avatar.png"}