{
  "name": "Eway.vn",
  "slug": "ewayvn",
  "website": "eway.vn",
  "industry": "Marketing",
  "tagline": "",
  "logoUrl": "",
  "description": "Established in 2009, Eway is a top-notch technology company with the passion for an ultimate Affiliate Marketing Ecosystem. With a pioneering and innovating spirit, our company works hard to provide the most effective Affiliate solutions. So far, Eway has built an enormous community of active publishers and advertisers worldwide, especially in the Asian e-Commerce market.\n\nOur belief focuses on the cutting-edge technology to take the lead and be the first, based on a stable and professional infrastructure, service and support. Eway also puts effort on growth hacking to predict and define the trends and upcoming demands of the industry to support our partner for the long term benefits. Kindly note that, when you choose to go with Eway, we do care about your long term journey to success.",
  "facebook": "fb.com/candichvulienlacvaoday",
  "linkedin": "linkedin.com/company/eway-jsc",
  "blogUrl": "",
  "androidUrl": "",
  "iosUrl": "",
  "demoUrl": "",
  "hiring": false
}