{
  "name": "iCheck",
  "slug": "icheck",
  "website": "icheck.com.vn/",
  "industry": "Software",
  "tagline": "",
  "logoUrl": "",
  "description": "iCheck Corporation develops mobile applications (iCheck Scanner & Barcode Viet with 10 million users), iCheck Code system (based on QR Code technology) and E-commerce platform (coming soon).",
  "facebook": "fb.com/iCheck.com.vn",
  "linkedin": "linkedin.com/company/icheckcorp",
  "blogUrl": "",
  "androidUrl": "https://play.google.com/store/apps/details?id=vn.icheck.android",
  "iosUrl": "https://apps.apple.com/app/id1001036590",
  "demoUrl": "",
  "hiring": false
}